s3sup/__init__.py
s3sup/catalogue.py
s3sup/fileprepper.py
s3sup/project.py
s3sup/rules.py
s3sup/rules.schema.json
s3sup/skeleton.s3sup.toml
s3sup/utils.py
s3sup/scripts/__init__.py
s3sup/scripts/s3sup.py
s3sup-0.5.0.dist-info/LICENSE.txt
s3sup-0.5.0.dist-info/METADATA
s3sup-0.5.0.dist-info/WHEEL
s3sup-0.5.0.dist-info/entry_points.txt
s3sup-0.5.0.dist-info/top_level.txt
s3sup-0.5.0.dist-info/RECORD
