Metadata-Version: 2.1
Name: s3sup
Version: 0.5.0
Summary: Static site uploader for Amazon S3
Home-page: https://github.com/awooldrige/s3sup
Author: Alistair Wooldrige
Author-email: s3sup@woolie.co.uk
License: UNKNOWN
Project-URL: Bug Reports, https://github.com/awooldrige/s3sup/issues
Project-URL: Source, https://github.com/awooldrige/s3sup/
Keywords: s3sup AWS S3 static
Platform: UNKNOWN
Classifier: Development Status :: 4 - Beta
Classifier: Intended Audience :: Developers
Classifier: License :: OSI Approved :: GNU General Public License v3 (GPLv3)
Classifier: Programming Language :: Python :: 3 :: Only
Classifier: Programming Language :: Python :: 3
Classifier: Programming Language :: Python :: 3.4
Classifier: Programming Language :: Python :: 3.5
Classifier: Programming Language :: Python :: 3.6
Classifier: Programming Language :: Python :: 3.7
Requires-Python: >=3, <4
Requires-Dist: boto3 (<2,>=1)
Requires-Dist: click (<9,>=7)
Requires-Dist: humanize (<1,>=0.4)
Requires-Dist: inflect (<3,>=2)
Requires-Dist: jsonschema (<4,>=2)
Requires-Dist: toml (<1,>=0.9)
Provides-Extra: test
Requires-Dist: flake8 ; extra == 'test'
Requires-Dist: moto ; extra == 'test'
